{
  "engine": "ember-template-lint",
  "filePath": "tests/dummy/app/templates/select.hbs",
  "ruleId": "no-action",
  "range": {
    "start": { "line": 10, "column": 17 },
    "end": { "line": 10, "column": 17 }
  },
  "source": "272b99b90dd53d4bdcbedf7056962e3bda74ebbb",
  "originalLintResult": {
    "rule": "no-action",
    "severity": 2,
    "filePath": "tests/dummy/app/templates/select.hbs",
    "line": 10,
    "column": 17,
    "endLine": 10,
    "endColumn": 42,
    "source": "(action (mut value) null)",
    "message": "Do not use `action` as (action ...). Instead, use the `on` modifier and `fn` helper."
  },
  "fileFormat": 2,
  "createdDate": 1694563200000,
  "warnDate": 1697155200000,
  "errorDate": 1699750800000
}
